check_deb_release/check_deb_release.py
check_deb_release-0.1.2.dist-info/licenses/LICENSE
check_deb_release-0.1.2.dist-info/METADATA
check_deb_release-0.1.2.dist-info/WHEEL
check_deb_release-0.1.2.dist-info/entry_points.txt
check_deb_release-0.1.2.dist-info/top_level.txt
check_deb_release-0.1.2.dist-info/RECORD
