Metadata-Version: 2.4
Name: check-deb-release
Version: 0.1.2
Summary: Check local debian version against a mirror and warn if a newer release is available.
Author-email: Bona Fide IT GmbH <github@bona-fide.it>, Olaf Rühenbeck <oruehenbeck@bona-fide.it>
License: MIT License
Project-URL: Homepage, https://github.com/BonaFideIT/check_deb_release
Keywords: icinga,nagios,plugin,check_command,debian,release,version
Classifier: License :: OSI Approved :: MIT License
Classifier: Programming Language :: Python
Classifier: Programming Language :: Python :: 3
Requires-Python: >=3.9
License-File: LICENSE
Requires-Dist: apt-repo>=0.5
Requires-Dist: nagiosplugin>=1.4.0
Requires-Dist: natsort>=8.4.0
Requires-Dist: validators>=0.35.0
Dynamic: license-file
